melado/__init__.py
melado/linear/__init__.py
melado/linear/adaline.py
melado/linear/perceptron.py
melado/linear/regression.py
melado/utils/__init__.py
melado/utils/error.py
tests/__init__.py
tests/test_linear_regression.py
tests/test_perceptron.py
melado-0.1.0.dist-info/LICENSE
melado-0.1.0.dist-info/METADATA
melado-0.1.0.dist-info/WHEEL
melado-0.1.0.dist-info/top_level.txt
melado-0.1.0.dist-info/RECORD
