Metadata-Version: 2.1
Name: melado
Version: 0.1.0
Summary: NumPy-based machine learning library
Home-page: https://github.com/luizmugnaini/melado
Author: Luiz Gustavo Mugnaini Anselmo
Author-email: luizmugnaini@gmail.com
License: MIT
Classifier: Programming Language :: Python :: 3
Classifier: License :: OSI Approved :: MIT License
Classifier: Operating System :: OS Independent
License-File: LICENSE
Requires-Dist: numpy
Requires-Dist: pandas
Requires-Dist: matplotlib
Requires-Dist: poetry
